README.rst
setup.py
douyin_image_yinlu/__init__.py
douyin_image_yinlu/converter.py
douyin_image_yinlu.egg-info/PKG-INFO
douyin_image_yinlu.egg-info/SOURCES.txt
douyin_image_yinlu.egg-info/dependency_links.txt
douyin_image_yinlu.egg-info/entry_points.txt
douyin_image_yinlu.egg-info/requires.txt
douyin_image_yinlu.egg-info/top_level.txt